setup.py
code/__init__.py
code/config.py
code/tap/__init__.py
code/tap/exceptions.py
code/tap/query.py
code/tap/upload.py
code/tap/utils.py
gaia_on_tap.egg-info/PKG-INFO
gaia_on_tap.egg-info/SOURCES.txt
gaia_on_tap.egg-info/dependency_links.txt
gaia_on_tap.egg-info/requires.txt
gaia_on_tap.egg-info/top_level.txt