Metadata-Version: 1.0
Name: gaia-on-tap
Version: 0.1.8
Summary: Utilities and tutorials for accessing Gaia data using TAP
Home-page: http://www.github.com/andycasey/gaia-on-tap/
Author: Andrew R. Casey
Author-email: andrew.casey@monash.edu
License: MIT
Platform: UNKNOWN
